django_openapi/__init__.py
django_openapi/api.py
django_openapi/cookie.py
django_openapi/params.py
django_openapi/route.py
django_openapi/utils.py
django_openapi/schema/__init__.py
django_openapi/schema/base.py
django_openapi/schema/fields/__init__.py
django_openapi/schema/fields/array.py
django_openapi/schema/fields/base.py
django_openapi/schema/fields/boolean.py
django_openapi/schema/fields/constants.py
django_openapi/schema/fields/exceptions.py
django_openapi/schema/fields/number.py
django_openapi/schema/fields/object.py
django_openapi/schema/fields/string.py
django_openapi/schema/fields/utils.py
django_openapi-0.1.1.11.dist-info/LICENSE
django_openapi-0.1.1.11.dist-info/METADATA
django_openapi-0.1.1.11.dist-info/WHEEL
django_openapi-0.1.1.11.dist-info/top_level.txt
django_openapi-0.1.1.11.dist-info/RECORD
