Metadata-Version: 2.1
Name: django-openapi
Version: 0.1.1.11
Summary: A minimal FastAPI implementation in python2 + Django without pydantic
Home-page: https://github.com/tokikanno/django-openapi
Author: toki kanno
Author-email: toki.kanno@gmail.com
License: UNKNOWN
Platform: UNKNOWN
Classifier: Development Status :: 3 - Alpha
Classifier: Environment :: Web Environment
Classifier: Framework :: Django
Classifier: License :: OSI Approved :: MIT License
Classifier: Programming Language :: Python
Classifier: Programming Language :: Python :: 2.7
Classifier: Programming Language :: Python :: 3
Classifier: Operating System :: OS Independent
Requires-Python: >=2.7
Requires-Dist: django
Requires-Dist: six
